Metadata-Version: 1.1
Name: plusplusgael
Version: 0.0.1
Summary: plusplusgael test
Home-page: https://github.com/rundimeco/plusplusgael
Author: UNKNOWN
Author-email: UNKNOWN
License: MIT
Platform: UNKNOWN
Classifier: Programming Language :: Python :: 3.6
